dcs/__init__.py
dcs/__main__.py
dcs/main.py
dcs/config/__init__.py
dcs/config/store.py
dcs/config/ui/__init__.py
dcs/config/ui/base.py
dcs/config/ui/enum_widget.py
dcs/config/ui/list_widget.py
dcs/config/ui/num_widget.py
dcs/config/ui/str_widget.py
dcs/config/ui/ui_create.py
dcs/frames/__init__.py
dcs/frames/base.py
dcs/frames/ch02_fourier.py
dcs/frames/ch02_phasor.py
dcs/frames/ch03_cross.py
dcs/frames/ch03_ergodic.py
dcs/frames/ch03_psd.py
dcs/frames/ch04_quantization_noise.py
dcs/frames/ch04_sampling.py
dcs/frames/ch04_window.py
dcs/frames/ch05_iq.py
dcs/frames/ch05_modulation.py
dcs/frames/ch05_qam.py
dcs/frames/ch06_down_sampling.py
dcs/frames/ch06_filter.py
dcs/frames/ch06_mixer.py
dcs/frames/ch06_up_sampling.py
dcs/frames/ch07_spreading.py
dcs/frames/groups.py
dcs/utils/__init__.py
dcs/utils/chain.py
dcs/utils/fft.py
dcs/utils/filter.py
dcs/utils/iq_mixer.py
dcs/utils/qam_modulation.py
dcs/utils/signal.py
dcs/utils/spreading.py
dcs/utils/symbols.py
dcs_interactive-1.0.2.dist-info/LICENSE
dcs_interactive-1.0.2.dist-info/METADATA
dcs_interactive-1.0.2.dist-info/WHEEL
dcs_interactive-1.0.2.dist-info/entry_points.txt
dcs_interactive-1.0.2.dist-info/top_level.txt
dcs_interactive-1.0.2.dist-info/RECORD
