Metadata-Version: 2.1
Name: dcs-interactive
Version: 1.0.2
Summary: Interactive Simulations and Visualizations for the Lecture in Digital Communication Systems
Author: Philipp Le
Author-email: philipp@philipple.de
Project-URL: Repository, https://gerrit.philipple.de/plugins/gitiles/dcs_interactive
Classifier: Development Status :: 2 - Pre-Alpha
Classifier: Environment :: Console
Classifier: Environment :: X11 Applications
Classifier: Environment :: Win32 (MS Windows)
Classifier: Intended Audience :: Education
Classifier: License :: OSI Approved :: Mozilla Public License 2.0 (MPL 2.0)
Classifier: Operating System :: MacOS :: MacOS X
Classifier: Operating System :: Microsoft :: Windows
Classifier: Operating System :: POSIX
Classifier: Programming Language :: Python
Classifier: Topic :: Education
Classifier: Topic :: Scientific/Engineering
Classifier: Typing :: Typed
License-File: LICENSE
Requires-Dist: numpy ~=1.26.2
Requires-Dist: scipy ~=1.11.4
Requires-Dist: matplotlib ~=3.8.2
Requires-Dist: toml ~=0.10.2
Requires-Dist: pydantic <2.0.0,>=1.0.0
Requires-Dist: appdirs ~=1.4.4
